[
    {
        "title": "Cake - Night And Day Choclate",
        "image": "http://dummyimage.com/156x231.bmp/cc0000/ffffff",
        "price": 31.02,
        "brand": "Music",
        "review_score": 4.88
    },
    {
        "title": "Juice - Apple Cider",
        "image": "http://dummyimage.com/103x153.bmp/ff4444/ffffff",
        "price": 2.3,
        "brand": "Outdoors",
        "review_score": 3.39
    },
    {
        "title": "Clementine",
        "image": "http://dummyimage.com/189x214.bmp/5fa2dd/ffffff",
        "price": 63.2,
        "brand": "Movies",
        "review_score": 3.0
    },
    {
        "title": "Muffin Hinge Container 6",
        "image": "http://dummyimage.com/206x249.bmp/dddddd/000000",
        "price": 70.33,
        "brand": "Sports",
        "review_score": 3.7
    },
    {
        "title": "Dawn Professionl Pot And Pan",
        "image": "http://dummyimage.com/120x113.bmp/dddddd/000000",
        "price": 96.39,
        "brand": "Kids",
        "review_score": 1.63
    },
    {
        "title": "Melon - Watermelon Yellow",
        "image": "http://dummyimage.com/192x142.png/5fa2dd/ffffff",
        "price": 6.16,
        "brand": "Garden",
        "review_score": 4.11
    },
    {
        "title": "Tomatoes - Orange",
        "image": "http://dummyimage.com/111x205.bmp/ff4444/ffffff",
        "price": 8.42,
        "brand": "Shoes",
        "review_score": 3.63
    },
    {
        "title": "Soup - Cream Of Broccoli",
        "image": "http://dummyimage.com/159x116.png/cc0000/ffffff",
        "price": 39.49,
        "brand": "Home",
        "review_score": 3.85
    },
    {
        "title": "Cup - 8oz Coffee Perforated",
        "image": "http://dummyimage.com/164x173.png/5fa2dd/ffffff",
        "price": 94.11,
        "brand": "Clothing",
        "review_score": 4.4
    },
    {
        "title": "Table Cloth 62x114 Colour",
        "image": "http://dummyimage.com/174x242.png/ff4444/ffffff",
        "price": 28.06,
        "brand": "Clothing",
        "review_score": 1.76
    },
    {
        "title": "Papayas",
        "image": "http://dummyimage.com/106x178.jpg/5fa2dd/ffffff",
        "price": 22.52,
        "brand": "Games",
        "review_score": 1.04
    },
    {
        "title": "Filo Dough",
        "image": "http://dummyimage.com/178x104.png/cc0000/ffffff",
        "price": 53.76,
        "brand": "Grocery",
        "review_score": 2.77
    },
    {
        "title": "Cake - Night And Day Choclate",
        "image": "http://dummyimage.com/147x244.png/dddddd/000000",
        "price": 25.91,
        "brand": "Electronics",
        "review_score": 2.22
    },
    {
        "title": "Scallops - U - 10",
        "image": "http://dummyimage.com/237x162.bmp/dddddd/000000",
        "price": 65.08,
        "brand": "Books",
        "review_score": 2.45
    },
    {
        "title": "Cheese - Goat With Herbs",
        "image": "http://dummyimage.com/114x117.jpg/ff4444/ffffff",
        "price": 4.5,
        "brand": "Tools",
        "review_score": 2.28
    },
    {
        "title": "Cookie Dough - Chocolate Chip",
        "image": "http://dummyimage.com/114x231.bmp/5fa2dd/ffffff",
        "price": 37.29,
        "brand": "Garden",
        "review_score": 2.83
    },
    {
        "title": "Pear - Packum",
        "image": "http://dummyimage.com/148x241.jpg/5fa2dd/ffffff",
        "price": 22.71,
        "brand": "Automotive",
        "review_score": 3.7
    },
    {
        "title": "Chocolate - Milk",
        "image": "http://dummyimage.com/153x109.bmp/ff4444/ffffff",
        "price": 83.98,
        "brand": "Electronics",
        "review_score": 3.22
    },
    {
        "title": "Truffle - Peelings",
        "image": "http://dummyimage.com/114x218.jpg/dddddd/000000",
        "price": 74.99,
        "brand": "Outdoors",
        "review_score": 1.17
    },
    {
        "title": "Table Cloth 62x120 Colour",
        "image": "http://dummyimage.com/109x126.jpg/dddddd/000000",
        "price": 38.66,
        "brand": "Home",
        "review_score": 3.6
    }
]